<feature_model name="34_120.xml">
<meta>
<data name="description">This is a 3-CNF Feature Model generated automatically</data>
<data name="creator">SPLOT Feature Model Generator</data>
<data name="email"></data>
<data name="date">Sun Apr 01 09:33:18 CEST 2018</data>
<data name="department">SPLOT Project</data>
<data name="organization">University of Waterloo</data>
<data name="address"></data>
<data name="phone"></data>
<data name="website">http://www.splot-research.org/</data>
<data name="reference">http://www.splot-research.org/</data>
</meta>
<feature_tree>
:r R(R)
	:o o_1(o_1)
		:o o_1_1(o_1_1)
		:m m_1_2(m_1_2)
		:m m_1_3(m_1_3)
	:o o_2(o_2)
		:o o_2_1(o_2_1)
		:o o_2_2(o_2_2)
		:m m_2_3(m_2_3)
	:o o_3(o_3)
		:o o_3_1(o_3_1)
			:o o_3_1_1(o_3_1_1)
		:o o_3_2(o_3_2)
			:o o_3_2_1(o_3_2_1)
	:o o_4(o_4)
		:o o_4_1(o_4_1)
			:o o_4_1_1(o_4_1_1)
		:o o_4_2(o_4_2)
			:o o_4_2_1(o_4_2_1)
	:m m_5(m_5)
		:m m_5_1(m_5_1)
		:o o_5_2(o_5_2)
		:m m_5_3(m_5_3)
	:o o_6(o_6)
		:o o_6_1(o_6_1)
		:o o_6_2(o_6_2)
		:o o_6_3(o_6_3)
	:m m_7(m_7)
		:o o_7_1(o_7_1)
		:o o_7_2(o_7_2)
	:o o_8(o_8)
		:o o_8_1(o_8_1)
			:o o_8_1_1(o_8_1_1)
	:o o_9(o_9)
		:o o_9_1(o_9_1)
		:o o_9_2(o_9_2)
	:o o_10(o_10)
		:o o_10_1(o_10_1)
		:o o_10_2(o_10_2)
	:o o_11(o_11)
		:o o_11_1(o_11_1)
		:o o_11_2(o_11_2)
		:o o_11_3(o_11_3)
	:o o_12(o_12)
		:o o_12_1(o_12_1)
		:o o_12_2(o_12_2)
		:o o_12_3(o_12_3)
	:o o_13(o_13)
		:o o_13_1(o_13_1)
		:o o_13_2(o_13_2)
		:o o_13_3(o_13_3)
	:o o_14(o_14)
		:o o_14_1(o_14_1)
		:o o_14_2(o_14_2)
		:m m_14_3(m_14_3)
	:o o_15(o_15)
		:m m_15_1(m_15_1)
		:o o_15_2(o_15_2)
		:m m_15_3(m_15_3)
	:o o_16(o_16)
		:o o_16_1(o_16_1)
		:o o_16_2(o_16_2)
		:m m_16_3(m_16_3)
	:o o_17(o_17)
		:o o_17_1(o_17_1)
		:o o_17_2(o_17_2)
		:o o_17_3(o_17_3)
	:o o_18(o_18)
		:o o_18_1(o_18_1)
		:o o_18_2(o_18_2)
		:o o_18_3(o_18_3)
	:o o_19(o_19)
		:o o_19_1(o_19_1)
		:m m_19_2(m_19_2)
		:o o_19_3(o_19_3)
	:o o_20(o_20)
		:o o_20_1(o_20_1)
		:m m_20_2(m_20_2)
		:o o_20_3(o_20_3)
	:m m_21(m_21)
		:o o_21_1(o_21_1)
		:o o_21_2(o_21_2)
		:o o_21_3(o_21_3)
	:o o_22(o_22)
		:m m_22_1(m_22_1)
		:o o_22_2(o_22_2)
		:o o_22_3(o_22_3)
	:o o_23(o_23)
		:o o_23_1(o_23_1)
		:o o_23_2(o_23_2)
		:o o_23_3(o_23_3)
	:o o_24(o_24)
		:o o_24_1(o_24_1)
		:o o_24_2(o_24_2)
		:o o_24_3(o_24_3)
	:o o_25(o_25)
		:o o_25_1(o_25_1)
			:o o_25_1_1(o_25_1_1)
		:o o_25_2(o_25_2)
			:o o_25_2_1(o_25_2_1)
	:o o_26(o_26)
		:o o_26_1(o_26_1)
		:o o_26_2(o_26_2)
		:o o_26_3(o_26_3)
	:o o_27(o_27)
		:m m_27_1(m_27_1)
		:o o_27_2(o_27_2)
		:o o_27_3(o_27_3)
	:o o_28(o_28)
		:o o_28_1(o_28_1)
		:o o_28_2(o_28_2)
		:m m_28_3(m_28_3)
	:o o_29(o_29)
		:o o_29_1(o_29_1)
		:o o_29_2(o_29_2)
		:o o_29_3(o_29_3)
	:o o_30(o_30)
		:o o_30_1(o_30_1)
		:o o_30_2(o_30_2)
		:o o_30_3(o_30_3)
</feature_tree>
<constraints>
Clause3CNF_1:~o_25 or o_29_2 or o_30_3
Clause3CNF_2:o_16_2 or o_30 or ~o_4_1_1
Clause3CNF_3:~o_20 or o_22_2 or o_2_2
Clause3CNF_4:~o_21_1 or ~o_3_1_1 or o_3_2_1
Clause3CNF_5:~m_22_1 or ~o_10_1 or ~o_14
Clause3CNF_6:m_5_1 or ~o_20 or ~o_21_3
Clause3CNF_7:m_28_3 or o_13_1 or ~o_6
Clause3CNF_8:o_22 or ~o_28_1 or ~o_3
Clause3CNF_9:m_15_1 or o_18 or o_4_2_1
Clause3CNF_10:o_14_1 or o_28_2 or ~o_30
Clause3CNF_11:o_17_2 or ~o_25 or o_9
Clause3CNF_12:m_27_1 or ~o_26_3 or o_30_2
Clause3CNF_13:~m_1_2 or ~m_21 or ~o_17_1
Clause3CNF_14:o_10_1 or ~o_22_3 or o_7_1
</constraints>
</feature_model>
