<feature_model name="/Users/rbean/temp/68_25.xml">
<meta>
<data name="description">This is a 3-CNF Feature Model generated automatically</data>
<data name="creator">SPLOT Feature Model Generator</data>
<data name="email"></data>
<data name="date">Wed Jan 03 21:27:42 CET 2018</data>
<data name="department">SPLOT Project</data>
<data name="organization">University of Waterloo</data>
<data name="address"></data>
<data name="phone"></data>
<data name="website">http://www.splot-research.org/</data>
<data name="reference">http://www.splot-research.org/</data>
</meta>
<feature_tree>
:r R(R)
	:o o_1(o_1)
		:o o_1_1(o_1_1)
		:o o_1_2(o_1_2)
		:g _Ge__1_3(_Ge__1_3) [1,1] 
			: g_1_3_1(g_1_3_1)
			: g_1_3_2(g_1_3_2)
			: g_1_3_3(g_1_3_3)
			: g_1_3_4(g_1_3_4)
	:o o_2(o_2)
		:o o_2_1(o_2_1)
	:o o_3(o_3)
		:g _Ge__3_1(_Ge__3_1) [1,1] 
			: g_3_1_1(g_3_1_1)
			: g_3_1_2(g_3_1_2)
		:o o_3_2(o_3_2)
		:o o_3_3(o_3_3)
	:g _Gi__4(_Gi__4) [1,*] 
		: g_4_1(g_4_1)
			:o o_4_1_1(o_4_1_1)
		: g_4_2(g_4_2)
			:o o_4_2_1(o_4_2_1)
	:o o_5(o_5)
		:o o_5_1(o_5_1)
	:o o_6(o_6)
		:o o_6_1(o_6_1)
		:o o_6_2(o_6_2)
		:o o_6_3(o_6_3)
</feature_tree>
<constraints>
Clause3CNF_1:~g_1_3_1 or g_3_1_1 or o_3_3
Clause3CNF_2:~g_3_1_2 or ~o_1_2 or ~o_4_1_1
Clause3CNF_3:g_1_3_4 or o_1_1 or o_3_2
Clause3CNF_4:g_3_1_1 or o_5_1 or o_6_2
Clause3CNF_5:o_3_3 or ~o_5 or o_5_1
Clause3CNF_6:~g_4_1 or o_1_1 or o_3_2
</constraints>
</feature_model>
